drop_privileges.py
setup.py
drop_privileges.egg-info/PKG-INFO
drop_privileges.egg-info/SOURCES.txt
drop_privileges.egg-info/dependency_links.txt
drop_privileges.egg-info/top_level.txt
