Metadata-Version: 1.0
Name: drop-privileges
Version: 0.1
Summary: Drop root privileges on a POSIX system.
Home-page: UNKNOWN
Author: Gavin Baker, Hartmut Goebel
Author-email: h.goebel@goebel-consult.de
License: MIT License
Platform: UNKNOWN
Classifier: Development Status :: 5 - Production/Stable
Classifier: Intended Audience :: Developers
Classifier: License :: OSI Approved :: MIT License
Classifier: Operating System :: POSIX
Classifier: Programming Language :: Python
Classifier: Topic :: Software Development :: Libraries :: Python Modules
